match.cpython-312-darwin.so
spritefridge/spritefridge.py
spritefridge/annotate/__init__.py
spritefridge/annotate/annotate.py
spritefridge/annotate/cli.py
spritefridge/annotate/core.py
spritefridge/annotate/ioutils.py
spritefridge/balance/__init__.py
spritefridge/balance/balance.py
spritefridge/balance/cli.py
spritefridge/balance/core.py
spritefridge/balance/ioutils.py
spritefridge/combine/__init__.py
spritefridge/combine/cli.py
spritefridge/combine/combine.py
spritefridge/combine/core.py
spritefridge/combine/ioutils.py
spritefridge/extractbc/__init__.py
spritefridge/extractbc/cli.py
spritefridge/extractbc/extract.py
spritefridge/extractbc/extractbc.py
spritefridge/extractbc/ioutils.py
spritefridge/extractbc/processors.py
spritefridge/pairs/__init__.py
spritefridge/pairs/cli.py
spritefridge/pairs/ioutils.py
spritefridge/pairs/pairs.py
spritefridge-1.4.1.dist-info/licenses/LICENSE
spritefridge-1.4.1.dist-info/METADATA
spritefridge-1.4.1.dist-info/WHEEL
spritefridge-1.4.1.dist-info/entry_points.txt
spritefridge-1.4.1.dist-info/top_level.txt
spritefridge-1.4.1.dist-info/RECORD
