Metadata-Version: 2.4
Name: spritefridge
Version: 1.4.1
Summary: A python toolbox for processing SPRITE-seq within the cooler universe
Author-email: Daniel Malzl <daniel@menchelab.com>
License: MIT License
Project-URL: Homepage, https://github.com/dmalzl/spritefridge
Keywords: bioinformatics,SPRITE sequencing,sequencing,NGS,cooler,barcode extraction,pairs file generation,4DN,3D genome
Classifier: License :: OSI Approved :: MIT License
Classifier: Programming Language :: Python
Classifier: Programming Language :: Python :: 3
Requires-Python: >=3.10
License-File: LICENSE
Requires-Dist: cooler>=0.10.2
Requires-Dist: pybedtools>=0.10.0
Requires-Dist: pysam>=0.22.1
Dynamic: license-file
